wy/__init__.py
wy/selenium.py
wy-0.0.3.dist-info/LICENSE
wy-0.0.3.dist-info/METADATA
wy-0.0.3.dist-info/WHEEL
wy-0.0.3.dist-info/top_level.txt
wy-0.0.3.dist-info/RECORD
