Metadata-Version: 2.1
Name: wy
Version: 0.0.3
Summary: Convenient tools for WayScript
Home-page: https://github.com/korakot/wy
Author: Korakot Chaovavanich
Author-email: korakot@gmail.com
License: UNKNOWN
Platform: UNKNOWN
Classifier: Programming Language :: Python :: 3
Classifier: License :: OSI Approved :: MIT License
Classifier: Operating System :: OS Independent
Requires-Python: >=3.6
